eufy_security_ws_python/__init__.py
eufy_security_ws_python/client.py
eufy_security_ws_python/const.py
eufy_security_ws_python/errors.py
eufy_security_ws_python/event.py
eufy_security_ws_python/model/__init__.py
eufy_security_ws_python/model/device.py
eufy_security_ws_python/model/driver.py
eufy_security_ws_python/model/station.py
eufy_security_ws_python/model/version.py
eufy_security_ws_python/version.py
eufy_security_ws_python-0.0.4.dist-info/LICENSE
eufy_security_ws_python-0.0.4.dist-info/WHEEL
eufy_security_ws_python-0.0.4.dist-info/METADATA
eufy_security_ws_python-0.0.4.dist-info/RECORD
