Metadata-Version: 2.1
Name: eufy-security-ws-python
Version: 0.0.4
Summary: A Python wrapper around eufy-security-ws
Home-page: https://github.com/bachya/eufy-security-ws-python
License: MIT
Author: Aaron Bach
Author-email: bachya1208@gmail.com
Requires-Python: >=3.6.1,<4.0.0
Classifier: License :: OSI Approved :: MIT License
Classifier: Programming Language :: Python
Classifier: Programming Language :: Python :: 3
Classifier: Programming Language :: Python :: 3.7
Classifier: Programming Language :: Python :: 3.8
Classifier: Programming Language :: Python :: 3.9
Classifier: Programming Language :: Python :: Implementation :: CPython
Classifier: Programming Language :: Python :: Implementation :: PyPy
Requires-Dist: aiohttp (>=3.7.4.post0,<4.0.0)
Project-URL: Repository, https://github.com/bachya/eufy-security-ws-python
